lazytext/__init__.py
lazytext/_repo_version.py
lazytext/cli.py
lazytext/create_table.py
lazytext/supervised.py
lazytext-0.0.2.dist-info/LICENSE
lazytext-0.0.2.dist-info/METADATA
lazytext-0.0.2.dist-info/WHEEL
lazytext-0.0.2.dist-info/entry_points.txt
lazytext-0.0.2.dist-info/top_level.txt
lazytext-0.0.2.dist-info/RECORD
