Metadata-Version: 2.1
Name: lazytext
Version: 0.0.2
Summary: UNKNOWN
Home-page: https://github.com/jdvala/lazytext
Author: lazytext
Author-email: jay.vala@msn.com
License: UNKNOWN
Platform: UNKNOWN
Classifier: Development Status :: 5 - Production/Stable
Classifier: Intended Audience :: Developers
Classifier: License :: OSI Approved :: MIT License
Classifier: Operating System :: OS Independent
Classifier: Programming Language :: Python :: 3.7
Classifier: Programming Language :: Python :: 3.8
Classifier: Topic :: Software Development :: Libraries :: Python Modules
Classifier: Topic :: Scientific/Engineering :: Artificial Intelligence
Classifier: Topic :: Scientific/Engineering
Classifier: Topic :: Text Processing :: General
Requires-Python: >=3.7.0
License-File: LICENSE
Requires-Dist: scikit-learn (==1.0.1)
Requires-Dist: rich (==11.2.0)
Requires-Dist: pandas (==1.3.5)
